{"train_loss": 0.018184788446252546, "val_loss": 0.012028315881888072, "val_psnr": 19.5752924132228, "val_ssim": 0.5855706132526199, "timestamp": 1726835721, "checkpoint_dir_name": null, "done": false, "training_iteration": 1, "trial_id": "6b602_00001", "date": "2024-09-20_19-35-21", "time_this_iter_s": 147.02205610275269, "time_total_s": 147.02205610275269, "pid": 170916, "hostname": "prism-2.apex.cmkl.ac.th", "node_ip": "172.16.101.112", "config": {"architecture": [64, 128, 256], "lr": 0.001, "batch_size": 16, "num_epochs": 10, "optimizer": "Adam"}, "time_since_restore": 147.02205610275269, "iterations_since_restore": 1}
{"train_loss": 0.013479124291489522, "val_loss": 0.01251655169079701, "val_psnr": 19.45269914775764, "val_ssim": 0.5985956757838528, "timestamp": 1726835856, "checkpoint_dir_name": null, "done": false, "training_iteration": 2, "trial_id": "6b602_00001", "date": "2024-09-20_19-37-36", "time_this_iter_s": 134.480060338974, "time_total_s": 281.5021164417267, "pid": 170916, "hostname": "prism-2.apex.cmkl.ac.th", "node_ip": "172.16.101.112", "config": {"architecture": [64, 128, 256], "lr": 0.001, "batch_size": 16, "num_epochs": 10, "optimizer": "Adam"}, "time_since_restore": 281.5021164417267, "iterations_since_restore": 2}
{"train_loss": 0.012006218730161588, "val_loss": 0.01134787763406833, "val_psnr": 19.96525686524984, "val_ssim": 0.6161380066970984, "timestamp": 1726835991, "checkpoint_dir_name": null, "done": false, "training_iteration": 3, "trial_id": "6b602_00001", "date": "2024-09-20_19-39-51", "time_this_iter_s": 135.39301586151123, "time_total_s": 416.8951323032379, "pid": 170916, "hostname": "prism-2.apex.cmkl.ac.th", "node_ip": "172.16.101.112", "config": {"architecture": [64, 128, 256], "lr": 0.001, "batch_size": 16, "num_epochs": 10, "optimizer": "Adam"}, "time_since_restore": 416.8951323032379, "iterations_since_restore": 3}
{"train_loss": 0.011381278491268555, "val_loss": 0.010230891377975544, "val_psnr": 20.383315512167204, "val_ssim": 0.6119020017472406, "timestamp": 1726836126, "checkpoint_dir_name": null, "done": false, "training_iteration": 4, "trial_id": "6b602_00001", "date": "2024-09-20_19-42-06", "time_this_iter_s": 135.17714428901672, "time_total_s": 552.0722765922546, "pid": 170916, "hostname": "prism-2.apex.cmkl.ac.th", "node_ip": "172.16.101.112", "config": {"architecture": [64, 128, 256], "lr": 0.001, "batch_size": 16, "num_epochs": 10, "optimizer": "Adam"}, "time_since_restore": 552.0722765922546, "iterations_since_restore": 4}
{"train_loss": 0.010734976769424975, "val_loss": 0.012261907038589318, "val_psnr": 19.52335775184406, "val_ssim": 0.5912817593788108, "timestamp": 1726836261, "checkpoint_dir_name": null, "done": false, "training_iteration": 5, "trial_id": "6b602_00001", "date": "2024-09-20_19-44-21", "time_this_iter_s": 134.4357032775879, "time_total_s": 686.5079798698425, "pid": 170916, "hostname": "prism-2.apex.cmkl.ac.th", "node_ip": "172.16.101.112", "config": {"architecture": [64, 128, 256], "lr": 0.001, "batch_size": 16, "num_epochs": 10, "optimizer": "Adam"}, "time_since_restore": 686.5079798698425, "iterations_since_restore": 5}
{"train_loss": 0.01054928629907469, "val_loss": 0.00999529838313659, "val_psnr": 20.35740812940247, "val_ssim": 0.6200334291507801, "timestamp": 1726836397, "checkpoint_dir_name": null, "done": false, "training_iteration": 6, "trial_id": "6b602_00001", "date": "2024-09-20_19-46-37", "time_this_iter_s": 136.13969898223877, "time_total_s": 822.6476788520813, "pid": 170916, "hostname": "prism-2.apex.cmkl.ac.th", "node_ip": "172.16.101.112", "config": {"architecture": [64, 128, 256], "lr": 0.001, "batch_size": 16, "num_epochs": 10, "optimizer": "Adam"}, "time_since_restore": 822.6476788520813, "iterations_since_restore": 6}
{"train_loss": 0.010125989620884259, "val_loss": 0.009758383405705293, "val_psnr": 20.527091547090343, "val_ssim": 0.6303738390505313, "timestamp": 1726836530, "checkpoint_dir_name": null, "done": false, "training_iteration": 7, "trial_id": "6b602_00001", "date": "2024-09-20_19-48-50", "time_this_iter_s": 133.61913323402405, "time_total_s": 956.2668120861053, "pid": 170916, "hostname": "prism-2.apex.cmkl.ac.th", "node_ip": "172.16.101.112", "config": {"architecture": [64, 128, 256], "lr": 0.001, "batch_size": 16, "num_epochs": 10, "optimizer": "Adam"}, "time_since_restore": 956.2668120861053, "iterations_since_restore": 7}
{"train_loss": 0.00996862833139797, "val_loss": 0.009447133818020424, "val_psnr": 20.663919855655553, "val_ssim": 0.6323408715178569, "timestamp": 1726836665, "checkpoint_dir_name": null, "done": false, "training_iteration": 8, "trial_id": "6b602_00001", "date": "2024-09-20_19-51-05", "time_this_iter_s": 134.75175070762634, "time_total_s": 1091.0185627937317, "pid": 170916, "hostname": "prism-2.apex.cmkl.ac.th", "node_ip": "172.16.101.112", "config": {"architecture": [64, 128, 256], "lr": 0.001, "batch_size": 16, "num_epochs": 10, "optimizer": "Adam"}, "time_since_restore": 1091.0185627937317, "iterations_since_restore": 8}
{"train_loss": 0.009736067625073095, "val_loss": 0.010083684358745813, "val_psnr": 20.454006029167964, "val_ssim": 0.6304776882976294, "timestamp": 1726836798, "checkpoint_dir_name": null, "done": false, "training_iteration": 9, "trial_id": "6b602_00001", "date": "2024-09-20_19-53-18", "time_this_iter_s": 133.1791009902954, "time_total_s": 1224.197663784027, "pid": 170916, "hostname": "prism-2.apex.cmkl.ac.th", "node_ip": "172.16.101.112", "config": {"architecture": [64, 128, 256], "lr": 0.001, "batch_size": 16, "num_epochs": 10, "optimizer": "Adam"}, "time_since_restore": 1224.197663784027, "iterations_since_restore": 9}
{"train_loss": 0.009635007317798833, "val_loss": 0.008833120007067919, "val_psnr": 20.951878652616852, "val_ssim": 0.6445392056504885, "timestamp": 1726836931, "checkpoint_dir_name": null, "done": false, "training_iteration": 10, "trial_id": "6b602_00001", "date": "2024-09-20_19-55-31", "time_this_iter_s": 132.16782522201538, "time_total_s": 1356.3654890060425, "pid": 170916, "hostname": "prism-2.apex.cmkl.ac.th", "node_ip": "172.16.101.112", "config": {"architecture": [64, 128, 256], "lr": 0.001, "batch_size": 16, "num_epochs": 10, "optimizer": "Adam"}, "time_since_restore": 1356.3654890060425, "iterations_since_restore": 10}
