{"train_loss": 0.021368869579358338, "val_loss": 0.015982264070771635, "val_psnr": 18.327728432116956, "val_ssim": 0.4658791415020824, "timestamp": 1727458696, "checkpoint_dir_name": null, "done": false, "training_iteration": 1, "trial_id": "b39b0_00014", "date": "2024-09-28_00-38-16", "time_this_iter_s": 137.11695194244385, "time_total_s": 137.11695194244385, "pid": 66568, "hostname": "prism-2.apex.cmkl.ac.th", "node_ip": "172.16.101.112", "config": {"architecture": [64, 128, 256], "lr": 0.005124045150195541, "batch_size": 25, "num_epochs": 33, "optimizer": "SGD"}, "time_since_restore": 137.11695194244385, "iterations_since_restore": 1}
{"train_loss": 0.016108038729483572, "val_loss": 0.014701055642217398, "val_psnr": 18.773474370284085, "val_ssim": 0.4934196696281433, "timestamp": 1727458833, "checkpoint_dir_name": null, "done": false, "training_iteration": 2, "trial_id": "b39b0_00014", "date": "2024-09-28_00-40-33", "time_this_iter_s": 137.00185537338257, "time_total_s": 274.1188073158264, "pid": 66568, "hostname": "prism-2.apex.cmkl.ac.th", "node_ip": "172.16.101.112", "config": {"architecture": [64, 128, 256], "lr": 0.005124045150195541, "batch_size": 25, "num_epochs": 33, "optimizer": "SGD"}, "time_since_restore": 274.1188073158264, "iterations_since_restore": 2}
{"train_loss": 0.01517899009922985, "val_loss": 0.01413571519466738, "val_psnr": 18.895448741929396, "val_ssim": 0.513558317201833, "timestamp": 1727458972, "checkpoint_dir_name": null, "done": false, "training_iteration": 3, "trial_id": "b39b0_00014", "date": "2024-09-28_00-42-52", "time_this_iter_s": 138.37020635604858, "time_total_s": 412.489013671875, "pid": 66568, "hostname": "prism-2.apex.cmkl.ac.th", "node_ip": "172.16.101.112", "config": {"architecture": [64, 128, 256], "lr": 0.005124045150195541, "batch_size": 25, "num_epochs": 33, "optimizer": "SGD"}, "time_since_restore": 412.489013671875, "iterations_since_restore": 3}
{"train_loss": 0.014712193852756173, "val_loss": 0.013491717190481723, "val_psnr": 19.100822090324744, "val_ssim": 0.5239139021858573, "timestamp": 1727459110, "checkpoint_dir_name": null, "done": false, "training_iteration": 4, "trial_id": "b39b0_00014", "date": "2024-09-28_00-45-10", "time_this_iter_s": 138.56417775154114, "time_total_s": 551.0531914234161, "pid": 66568, "hostname": "prism-2.apex.cmkl.ac.th", "node_ip": "172.16.101.112", "config": {"architecture": [64, 128, 256], "lr": 0.005124045150195541, "batch_size": 25, "num_epochs": 33, "optimizer": "SGD"}, "time_since_restore": 551.0531914234161, "iterations_since_restore": 4}
{"train_loss": 0.014279180946565854, "val_loss": 0.013264011704207709, "val_psnr": 19.160643293799513, "val_ssim": 0.5300109433531761, "timestamp": 1727459249, "checkpoint_dir_name": null, "done": false, "training_iteration": 5, "trial_id": "b39b0_00014", "date": "2024-09-28_00-47-29", "time_this_iter_s": 138.95953488349915, "time_total_s": 690.0127263069153, "pid": 66568, "hostname": "prism-2.apex.cmkl.ac.th", "node_ip": "172.16.101.112", "config": {"architecture": [64, 128, 256], "lr": 0.005124045150195541, "batch_size": 25, "num_epochs": 33, "optimizer": "SGD"}, "time_since_restore": 690.0127263069153, "iterations_since_restore": 5}
{"train_loss": 0.014034175090879822, "val_loss": 0.012934328157765169, "val_psnr": 19.27643949324369, "val_ssim": 0.5372781677121917, "timestamp": 1727459390, "checkpoint_dir_name": null, "done": false, "training_iteration": 6, "trial_id": "b39b0_00014", "date": "2024-09-28_00-49-50", "time_this_iter_s": 140.43648552894592, "time_total_s": 830.4492118358612, "pid": 66568, "hostname": "prism-2.apex.cmkl.ac.th", "node_ip": "172.16.101.112", "config": {"architecture": [64, 128, 256], "lr": 0.005124045150195541, "batch_size": 25, "num_epochs": 33, "optimizer": "SGD"}, "time_since_restore": 830.4492118358612, "iterations_since_restore": 6}
{"train_loss": 0.013803001367098963, "val_loss": 0.01279108327968667, "val_psnr": 19.31409740189193, "val_ssim": 0.5402953987692793, "timestamp": 1727459529, "checkpoint_dir_name": null, "done": false, "training_iteration": 7, "trial_id": "b39b0_00014", "date": "2024-09-28_00-52-09", "time_this_iter_s": 139.51897740364075, "time_total_s": 969.968189239502, "pid": 66568, "hostname": "prism-2.apex.cmkl.ac.th", "node_ip": "172.16.101.112", "config": {"architecture": [64, 128, 256], "lr": 0.005124045150195541, "batch_size": 25, "num_epochs": 33, "optimizer": "SGD"}, "time_since_restore": 969.968189239502, "iterations_since_restore": 7}
{"train_loss": 0.013763570792313355, "val_loss": 0.012671268545091152, "val_psnr": 19.378691451842162, "val_ssim": 0.5442924045274655, "timestamp": 1727459673, "checkpoint_dir_name": null, "done": false, "training_iteration": 8, "trial_id": "b39b0_00014", "date": "2024-09-28_00-54-33", "time_this_iter_s": 144.073317527771, "time_total_s": 1114.041506767273, "pid": 66568, "hostname": "prism-2.apex.cmkl.ac.th", "node_ip": "172.16.101.112", "config": {"architecture": [64, 128, 256], "lr": 0.005124045150195541, "batch_size": 25, "num_epochs": 33, "optimizer": "SGD"}, "time_since_restore": 1114.041506767273, "iterations_since_restore": 8}
{"train_loss": 0.013592451394652016, "val_loss": 0.012513039164089908, "val_psnr": 19.398245816530906, "val_ssim": 0.5452777124394973, "timestamp": 1727459845, "checkpoint_dir_name": null, "done": false, "training_iteration": 9, "trial_id": "b39b0_00014", "date": "2024-09-28_00-57-25", "time_this_iter_s": 171.47621178627014, "time_total_s": 1285.517718553543, "pid": 66568, "hostname": "prism-2.apex.cmkl.ac.th", "node_ip": "172.16.101.112", "config": {"architecture": [64, 128, 256], "lr": 0.005124045150195541, "batch_size": 25, "num_epochs": 33, "optimizer": "SGD"}, "time_since_restore": 1285.517718553543, "iterations_since_restore": 9}
{"train_loss": 0.013458004115576235, "val_loss": 0.012468312517739832, "val_psnr": 19.45207974851224, "val_ssim": 0.5499747474292914, "timestamp": 1727459990, "checkpoint_dir_name": null, "done": false, "training_iteration": 10, "trial_id": "b39b0_00014", "date": "2024-09-28_00-59-50", "time_this_iter_s": 145.22267985343933, "time_total_s": 1430.7403984069824, "pid": 66568, "hostname": "prism-2.apex.cmkl.ac.th", "node_ip": "172.16.101.112", "config": {"architecture": [64, 128, 256], "lr": 0.005124045150195541, "batch_size": 25, "num_epochs": 33, "optimizer": "SGD"}, "time_since_restore": 1430.7403984069824, "iterations_since_restore": 10}
{"train_loss": 0.013353130968365197, "val_loss": 0.012372204284959783, "val_psnr": 19.47890254275514, "val_ssim": 0.5528932236110171, "timestamp": 1727460139, "checkpoint_dir_name": null, "done": false, "training_iteration": 11, "trial_id": "b39b0_00014", "date": "2024-09-28_01-02-19", "time_this_iter_s": 149.29342579841614, "time_total_s": 1580.0338242053986, "pid": 66568, "hostname": "prism-2.apex.cmkl.ac.th", "node_ip": "172.16.101.112", "config": {"architecture": [64, 128, 256], "lr": 0.005124045150195541, "batch_size": 25, "num_epochs": 33, "optimizer": "SGD"}, "time_since_restore": 1580.0338242053986, "iterations_since_restore": 11}
{"train_loss": 0.01330622356326785, "val_loss": 0.012243922310881316, "val_psnr": 19.509354593982835, "val_ssim": 0.5538180054451028, "timestamp": 1727460284, "checkpoint_dir_name": null, "done": false, "training_iteration": 12, "trial_id": "b39b0_00014", "date": "2024-09-28_01-04-44", "time_this_iter_s": 144.97190046310425, "time_total_s": 1725.0057246685028, "pid": 66568, "hostname": "prism-2.apex.cmkl.ac.th", "node_ip": "172.16.101.112", "config": {"architecture": [64, 128, 256], "lr": 0.005124045150195541, "batch_size": 25, "num_epochs": 33, "optimizer": "SGD"}, "time_since_restore": 1725.0057246685028, "iterations_since_restore": 12}
{"train_loss": 0.01323383185469235, "val_loss": 0.012184736800069611, "val_psnr": 19.517554726737817, "val_ssim": 0.554264213087658, "timestamp": 1727460424, "checkpoint_dir_name": null, "done": false, "training_iteration": 13, "trial_id": "b39b0_00014", "date": "2024-09-28_01-07-04", "time_this_iter_s": 140.26568937301636, "time_total_s": 1865.2714140415192, "pid": 66568, "hostname": "prism-2.apex.cmkl.ac.th", "node_ip": "172.16.101.112", "config": {"architecture": [64, 128, 256], "lr": 0.005124045150195541, "batch_size": 25, "num_epochs": 33, "optimizer": "SGD"}, "time_since_restore": 1865.2714140415192, "iterations_since_restore": 13}
{"train_loss": 0.013083920724845181, "val_loss": 0.012589419132564218, "val_psnr": 19.439434324200036, "val_ssim": 0.5567246492157379, "timestamp": 1727460570, "checkpoint_dir_name": null, "done": false, "training_iteration": 14, "trial_id": "b39b0_00014", "date": "2024-09-28_01-09-30", "time_this_iter_s": 145.53291296958923, "time_total_s": 2010.8043270111084, "pid": 66568, "hostname": "prism-2.apex.cmkl.ac.th", "node_ip": "172.16.101.112", "config": {"architecture": [64, 128, 256], "lr": 0.005124045150195541, "batch_size": 25, "num_epochs": 33, "optimizer": "SGD"}, "time_since_restore": 2010.8043270111084, "iterations_since_restore": 14}
{"train_loss": 0.012960612580839855, "val_loss": 0.012153488343271117, "val_psnr": 19.544579172444802, "val_ssim": 0.5563688255200784, "timestamp": 1727460725, "checkpoint_dir_name": null, "done": false, "training_iteration": 15, "trial_id": "b39b0_00014", "date": "2024-09-28_01-12-05", "time_this_iter_s": 155.2213306427002, "time_total_s": 2166.0256576538086, "pid": 66568, "hostname": "prism-2.apex.cmkl.ac.th", "node_ip": "172.16.101.112", "config": {"architecture": [64, 128, 256], "lr": 0.005124045150195541, "batch_size": 25, "num_epochs": 33, "optimizer": "SGD"}, "time_since_restore": 2166.0256576538086, "iterations_since_restore": 15}
{"train_loss": 0.012861702498048544, "val_loss": 0.012090903101488948, "val_psnr": 19.538504892642752, "val_ssim": 0.5575452429006497, "timestamp": 1727460869, "checkpoint_dir_name": null, "done": false, "training_iteration": 16, "trial_id": "b39b0_00014", "date": "2024-09-28_01-14-29", "time_this_iter_s": 143.94730854034424, "time_total_s": 2309.972966194153, "pid": 66568, "hostname": "prism-2.apex.cmkl.ac.th", "node_ip": "172.16.101.112", "config": {"architecture": [64, 128, 256], "lr": 0.005124045150195541, "batch_size": 25, "num_epochs": 33, "optimizer": "SGD"}, "time_since_restore": 2309.972966194153, "iterations_since_restore": 16}
{"train_loss": 0.012877619802990618, "val_loss": 0.012019126528563599, "val_psnr": 19.60133187019281, "val_ssim": 0.5619879159058134, "timestamp": 1727461009, "checkpoint_dir_name": null, "done": false, "training_iteration": 17, "trial_id": "b39b0_00014", "date": "2024-09-28_01-16-49", "time_this_iter_s": 139.68836283683777, "time_total_s": 2449.6613290309906, "pid": 66568, "hostname": "prism-2.apex.cmkl.ac.th", "node_ip": "172.16.101.112", "config": {"architecture": [64, 128, 256], "lr": 0.005124045150195541, "batch_size": 25, "num_epochs": 33, "optimizer": "SGD"}, "time_since_restore": 2449.6613290309906, "iterations_since_restore": 17}
{"train_loss": 0.012890239409171046, "val_loss": 0.011968757390665512, "val_psnr": 19.614612213080353, "val_ssim": 0.5614127980917692, "timestamp": 1727461154, "checkpoint_dir_name": null, "done": false, "training_iteration": 18, "trial_id": "b39b0_00014", "date": "2024-09-28_01-19-14", "time_this_iter_s": 144.74291968345642, "time_total_s": 2594.404248714447, "pid": 66568, "hostname": "prism-2.apex.cmkl.ac.th", "node_ip": "172.16.101.112", "config": {"architecture": [64, 128, 256], "lr": 0.005124045150195541, "batch_size": 25, "num_epochs": 33, "optimizer": "SGD"}, "time_since_restore": 2594.404248714447, "iterations_since_restore": 18}
{"train_loss": 0.012678978348655315, "val_loss": 0.011885876658683021, "val_psnr": 19.6512890711674, "val_ssim": 0.5632166837354501, "timestamp": 1727461288, "checkpoint_dir_name": null, "done": false, "training_iteration": 19, "trial_id": "b39b0_00014", "date": "2024-09-28_01-21-28", "time_this_iter_s": 134.03340077400208, "time_total_s": 2728.437649488449, "pid": 66568, "hostname": "prism-2.apex.cmkl.ac.th", "node_ip": "172.16.101.112", "config": {"architecture": [64, 128, 256], "lr": 0.005124045150195541, "batch_size": 25, "num_epochs": 33, "optimizer": "SGD"}, "time_since_restore": 2728.437649488449, "iterations_since_restore": 19}
{"train_loss": 0.012716943325358443, "val_loss": 0.011790549374806385, "val_psnr": 19.676650486628414, "val_ssim": 0.5638022884900371, "timestamp": 1727461414, "checkpoint_dir_name": null, "done": false, "training_iteration": 20, "trial_id": "b39b0_00014", "date": "2024-09-28_01-23-34", "time_this_iter_s": 126.01094555854797, "time_total_s": 2854.448595046997, "pid": 66568, "hostname": "prism-2.apex.cmkl.ac.th", "node_ip": "172.16.101.112", "config": {"architecture": [64, 128, 256], "lr": 0.005124045150195541, "batch_size": 25, "num_epochs": 33, "optimizer": "SGD"}, "time_since_restore": 2854.448595046997, "iterations_since_restore": 20}
{"train_loss": 0.012565740534531264, "val_loss": 0.011768707423470914, "val_psnr": 19.67335239718685, "val_ssim": 0.5648430050363143, "timestamp": 1727461543, "checkpoint_dir_name": null, "done": false, "training_iteration": 21, "trial_id": "b39b0_00014", "date": "2024-09-28_01-25-43", "time_this_iter_s": 129.6612901687622, "time_total_s": 2984.1098852157593, "pid": 66568, "hostname": "prism-2.apex.cmkl.ac.th", "node_ip": "172.16.101.112", "config": {"architecture": [64, 128, 256], "lr": 0.005124045150195541, "batch_size": 25, "num_epochs": 33, "optimizer": "SGD"}, "time_since_restore": 2984.1098852157593, "iterations_since_restore": 21}
{"train_loss": 0.012559439716278575, "val_loss": 0.011820935042730222, "val_psnr": 19.69039317823837, "val_ssim": 0.5666047541449467, "timestamp": 1727461687, "checkpoint_dir_name": null, "done": false, "training_iteration": 22, "trial_id": "b39b0_00014", "date": "2024-09-28_01-28-07", "time_this_iter_s": 143.28759813308716, "time_total_s": 3127.3974833488464, "pid": 66568, "hostname": "prism-2.apex.cmkl.ac.th", "node_ip": "172.16.101.112", "config": {"architecture": [64, 128, 256], "lr": 0.005124045150195541, "batch_size": 25, "num_epochs": 33, "optimizer": "SGD"}, "time_since_restore": 3127.3974833488464, "iterations_since_restore": 22}
{"train_loss": 0.012560612574452535, "val_loss": 0.011763752232460926, "val_psnr": 19.71167134405903, "val_ssim": 0.5673774186571439, "timestamp": 1727461822, "checkpoint_dir_name": null, "done": false, "training_iteration": 23, "trial_id": "b39b0_00014", "date": "2024-09-28_01-30-22", "time_this_iter_s": 135.5636556148529, "time_total_s": 3262.9611389636993, "pid": 66568, "hostname": "prism-2.apex.cmkl.ac.th", "node_ip": "172.16.101.112", "config": {"architecture": [64, 128, 256], "lr": 0.005124045150195541, "batch_size": 25, "num_epochs": 33, "optimizer": "SGD"}, "time_since_restore": 3262.9611389636993, "iterations_since_restore": 23}
{"train_loss": 0.012457503232872114, "val_loss": 0.011804451952533176, "val_psnr": 19.649584278056434, "val_ssim": 0.5636782943134506, "timestamp": 1727461952, "checkpoint_dir_name": null, "done": false, "training_iteration": 24, "trial_id": "b39b0_00014", "date": "2024-09-28_01-32-32", "time_this_iter_s": 129.4781379699707, "time_total_s": 3392.43927693367, "pid": 66568, "hostname": "prism-2.apex.cmkl.ac.th", "node_ip": "172.16.101.112", "config": {"architecture": [64, 128, 256], "lr": 0.005124045150195541, "batch_size": 25, "num_epochs": 33, "optimizer": "SGD"}, "time_since_restore": 3392.43927693367, "iterations_since_restore": 24}
{"train_loss": 0.012419000499842998, "val_loss": 0.011922661071488013, "val_psnr": 19.646612810940493, "val_ssim": 0.5675634779681762, "timestamp": 1727462084, "checkpoint_dir_name": null, "done": false, "training_iteration": 25, "trial_id": "b39b0_00014", "date": "2024-09-28_01-34-44", "time_this_iter_s": 131.8781385421753, "time_total_s": 3524.3174154758453, "pid": 66568, "hostname": "prism-2.apex.cmkl.ac.th", "node_ip": "172.16.101.112", "config": {"architecture": [64, 128, 256], "lr": 0.005124045150195541, "batch_size": 25, "num_epochs": 33, "optimizer": "SGD"}, "time_since_restore": 3524.3174154758453, "iterations_since_restore": 25}
{"train_loss": 0.012344726163428276, "val_loss": 0.011671994001759837, "val_psnr": 19.70474353621814, "val_ssim": 0.5665933360333244, "timestamp": 1727462211, "checkpoint_dir_name": null, "done": false, "training_iteration": 26, "trial_id": "b39b0_00014", "date": "2024-09-28_01-36-51", "time_this_iter_s": 127.42167091369629, "time_total_s": 3651.7390863895416, "pid": 66568, "hostname": "prism-2.apex.cmkl.ac.th", "node_ip": "172.16.101.112", "config": {"architecture": [64, 128, 256], "lr": 0.005124045150195541, "batch_size": 25, "num_epochs": 33, "optimizer": "SGD"}, "time_since_restore": 3651.7390863895416, "iterations_since_restore": 26}
{"train_loss": 0.012310956556272382, "val_loss": 0.011760599934495986, "val_psnr": 19.7096293720633, "val_ssim": 0.56993374406298, "timestamp": 1727462339, "checkpoint_dir_name": null, "done": false, "training_iteration": 27, "trial_id": "b39b0_00014", "date": "2024-09-28_01-38-59", "time_this_iter_s": 128.0287845134735, "time_total_s": 3779.767870903015, "pid": 66568, "hostname": "prism-2.apex.cmkl.ac.th", "node_ip": "172.16.101.112", "config": {"architecture": [64, 128, 256], "lr": 0.005124045150195541, "batch_size": 25, "num_epochs": 33, "optimizer": "SGD"}, "time_since_restore": 3779.767870903015, "iterations_since_restore": 27}
{"train_loss": 0.01233957758716618, "val_loss": 0.011589088403464605, "val_psnr": 19.748622498830226, "val_ssim": 0.5696363291318218, "timestamp": 1727462470, "checkpoint_dir_name": null, "done": false, "training_iteration": 28, "trial_id": "b39b0_00014", "date": "2024-09-28_01-41-10", "time_this_iter_s": 130.43567967414856, "time_total_s": 3910.2035505771637, "pid": 66568, "hostname": "prism-2.apex.cmkl.ac.th", "node_ip": "172.16.101.112", "config": {"architecture": [64, 128, 256], "lr": 0.005124045150195541, "batch_size": 25, "num_epochs": 33, "optimizer": "SGD"}, "time_since_restore": 3910.2035505771637, "iterations_since_restore": 28}
{"train_loss": 0.012354173220228405, "val_loss": 0.011667141640403618, "val_psnr": 19.71955766076723, "val_ssim": 0.5678350140104691, "timestamp": 1727462601, "checkpoint_dir_name": null, "done": false, "training_iteration": 29, "trial_id": "b39b0_00014", "date": "2024-09-28_01-43-21", "time_this_iter_s": 131.1510214805603, "time_total_s": 4041.354572057724, "pid": 66568, "hostname": "prism-2.apex.cmkl.ac.th", "node_ip": "172.16.101.112", "config": {"architecture": [64, 128, 256], "lr": 0.005124045150195541, "batch_size": 25, "num_epochs": 33, "optimizer": "SGD"}, "time_since_restore": 4041.354572057724, "iterations_since_restore": 29}
{"train_loss": 0.012291407595815448, "val_loss": 0.01154086416742454, "val_psnr": 19.75006129765751, "val_ssim": 0.569265911243856, "timestamp": 1727462733, "checkpoint_dir_name": null, "done": false, "training_iteration": 30, "trial_id": "b39b0_00014", "date": "2024-09-28_01-45-33", "time_this_iter_s": 132.46328139305115, "time_total_s": 4173.817853450775, "pid": 66568, "hostname": "prism-2.apex.cmkl.ac.th", "node_ip": "172.16.101.112", "config": {"architecture": [64, 128, 256], "lr": 0.005124045150195541, "batch_size": 25, "num_epochs": 33, "optimizer": "SGD"}, "time_since_restore": 4173.817853450775, "iterations_since_restore": 30}
{"train_loss": 0.01222342275432311, "val_loss": 0.011493664867399882, "val_psnr": 19.78917431286826, "val_ssim": 0.5713631056770683, "timestamp": 1727462865, "checkpoint_dir_name": null, "done": false, "training_iteration": 31, "trial_id": "b39b0_00014", "date": "2024-09-28_01-47-45", "time_this_iter_s": 131.4121322631836, "time_total_s": 4305.229985713959, "pid": 66568, "hostname": "prism-2.apex.cmkl.ac.th", "node_ip": "172.16.101.112", "config": {"architecture": [64, 128, 256], "lr": 0.005124045150195541, "batch_size": 25, "num_epochs": 33, "optimizer": "SGD"}, "time_since_restore": 4305.229985713959, "iterations_since_restore": 31}
{"train_loss": 0.012180817474533494, "val_loss": 0.011291457957122475, "val_psnr": 19.84712949814364, "val_ssim": 0.5718974522650242, "timestamp": 1727462994, "checkpoint_dir_name": null, "done": false, "training_iteration": 32, "trial_id": "b39b0_00014", "date": "2024-09-28_01-49-54", "time_this_iter_s": 129.7190546989441, "time_total_s": 4434.949040412903, "pid": 66568, "hostname": "prism-2.apex.cmkl.ac.th", "node_ip": "172.16.101.112", "config": {"architecture": [64, 128, 256], "lr": 0.005124045150195541, "batch_size": 25, "num_epochs": 33, "optimizer": "SGD"}, "time_since_restore": 4434.949040412903, "iterations_since_restore": 32}
{"train_loss": 0.012091885088981751, "val_loss": 0.0114557719284979, "val_psnr": 19.810965550241697, "val_ssim": 0.5722966782152653, "timestamp": 1727463125, "checkpoint_dir_name": null, "done": false, "training_iteration": 33, "trial_id": "b39b0_00014", "date": "2024-09-28_01-52-05", "time_this_iter_s": 130.5593888759613, "time_total_s": 4565.508429288864, "pid": 66568, "hostname": "prism-2.apex.cmkl.ac.th", "node_ip": "172.16.101.112", "config": {"architecture": [64, 128, 256], "lr": 0.005124045150195541, "batch_size": 25, "num_epochs": 33, "optimizer": "SGD"}, "time_since_restore": 4565.508429288864, "iterations_since_restore": 33}
