{"train_loss": 0.04273664109641686, "val_loss": 0.02586292101070285, "val_psnr": 16.142842579602082, "val_ssim": 0.3107477529123425, "timestamp": 1727445719, "checkpoint_dir_name": null, "done": false, "training_iteration": 1, "trial_id": "b39b0_00011", "date": "2024-09-27_21-01-59", "time_this_iter_s": 145.04234337806702, "time_total_s": 145.04234337806702, "pid": 4097730, "hostname": "prism-2.apex.cmkl.ac.th", "node_ip": "172.16.101.112", "config": {"architecture": [64, 128, 256], "lr": 0.0007611817967705463, "batch_size": 30, "num_epochs": 82, "optimizer": "SGD"}, "time_since_restore": 145.04234337806702, "iterations_since_restore": 1}
{"train_loss": 0.02414019618416205, "val_loss": 0.021156384646892547, "val_psnr": 17.038459414303947, "val_ssim": 0.3625180584092935, "timestamp": 1727445862, "checkpoint_dir_name": null, "done": false, "training_iteration": 2, "trial_id": "b39b0_00011", "date": "2024-09-27_21-04-22", "time_this_iter_s": 143.33088994026184, "time_total_s": 288.37323331832886, "pid": 4097730, "hostname": "prism-2.apex.cmkl.ac.th", "node_ip": "172.16.101.112", "config": {"architecture": [64, 128, 256], "lr": 0.0007611817967705463, "batch_size": 30, "num_epochs": 82, "optimizer": "SGD"}, "time_since_restore": 288.37323331832886, "iterations_since_restore": 2}
{"train_loss": 0.021053831197787077, "val_loss": 0.01938773602247238, "val_psnr": 17.438411312243215, "val_ssim": 0.3930054894809922, "timestamp": 1727446007, "checkpoint_dir_name": null, "done": false, "training_iteration": 3, "trial_id": "b39b0_00011", "date": "2024-09-27_21-06-47", "time_this_iter_s": 144.54891777038574, "time_total_s": 432.9221510887146, "pid": 4097730, "hostname": "prism-2.apex.cmkl.ac.th", "node_ip": "172.16.101.112", "config": {"architecture": [64, 128, 256], "lr": 0.0007611817967705463, "batch_size": 30, "num_epochs": 82, "optimizer": "SGD"}, "time_since_restore": 432.9221510887146, "iterations_since_restore": 3}
{"train_loss": 0.019463119922438637, "val_loss": 0.018188573173247277, "val_psnr": 17.721201149641615, "val_ssim": 0.412381036773324, "timestamp": 1727446150, "checkpoint_dir_name": null, "done": false, "training_iteration": 4, "trial_id": "b39b0_00011", "date": "2024-09-27_21-09-10", "time_this_iter_s": 142.7824788093567, "time_total_s": 575.7046298980713, "pid": 4097730, "hostname": "prism-2.apex.cmkl.ac.th", "node_ip": "172.16.101.112", "config": {"architecture": [64, 128, 256], "lr": 0.0007611817967705463, "batch_size": 30, "num_epochs": 82, "optimizer": "SGD"}, "time_since_restore": 575.7046298980713, "iterations_since_restore": 4}
{"train_loss": 0.01856294242432341, "val_loss": 0.017215425092726947, "val_psnr": 17.969048743217353, "val_ssim": 0.4293535614460707, "timestamp": 1727446300, "checkpoint_dir_name": null, "done": false, "training_iteration": 5, "trial_id": "b39b0_00011", "date": "2024-09-27_21-11-40", "time_this_iter_s": 149.8389036655426, "time_total_s": 725.5435335636139, "pid": 4097730, "hostname": "prism-2.apex.cmkl.ac.th", "node_ip": "172.16.101.112", "config": {"architecture": [64, 128, 256], "lr": 0.0007611817967705463, "batch_size": 30, "num_epochs": 82, "optimizer": "SGD"}, "time_since_restore": 725.5435335636139, "iterations_since_restore": 5}
{"train_loss": 0.017819511860143394, "val_loss": 0.016655899165198208, "val_psnr": 18.11741196913836, "val_ssim": 0.440885455660522, "timestamp": 1727446443, "checkpoint_dir_name": null, "done": false, "training_iteration": 6, "trial_id": "b39b0_00011", "date": "2024-09-27_21-14-03", "time_this_iter_s": 143.3217113018036, "time_total_s": 868.8652448654175, "pid": 4097730, "hostname": "prism-2.apex.cmkl.ac.th", "node_ip": "172.16.101.112", "config": {"architecture": [64, 128, 256], "lr": 0.0007611817967705463, "batch_size": 30, "num_epochs": 82, "optimizer": "SGD"}, "time_since_restore": 868.8652448654175, "iterations_since_restore": 6}
{"train_loss": 0.017262045594397934, "val_loss": 0.016272943657822905, "val_psnr": 18.2402220583385, "val_ssim": 0.45190003524223965, "timestamp": 1727446588, "checkpoint_dir_name": null, "done": false, "training_iteration": 7, "trial_id": "b39b0_00011", "date": "2024-09-27_21-16-28", "time_this_iter_s": 144.6189262866974, "time_total_s": 1013.4841711521149, "pid": 4097730, "hostname": "prism-2.apex.cmkl.ac.th", "node_ip": "172.16.101.112", "config": {"architecture": [64, 128, 256], "lr": 0.0007611817967705463, "batch_size": 30, "num_epochs": 82, "optimizer": "SGD"}, "time_since_restore": 1013.4841711521149, "iterations_since_restore": 7}
{"train_loss": 0.01693109725601971, "val_loss": 0.0160104845976457, "val_psnr": 18.302736947339092, "val_ssim": 0.45974874526510634, "timestamp": 1727446731, "checkpoint_dir_name": null, "done": false, "training_iteration": 8, "trial_id": "b39b0_00011", "date": "2024-09-27_21-18-51", "time_this_iter_s": 143.5683662891388, "time_total_s": 1157.0525374412537, "pid": 4097730, "hostname": "prism-2.apex.cmkl.ac.th", "node_ip": "172.16.101.112", "config": {"architecture": [64, 128, 256], "lr": 0.0007611817967705463, "batch_size": 30, "num_epochs": 82, "optimizer": "SGD"}, "time_since_restore": 1157.0525374412537, "iterations_since_restore": 8}
{"train_loss": 0.016596149198012427, "val_loss": 0.015655518313869833, "val_psnr": 18.402553609226096, "val_ssim": 0.4669657524600625, "timestamp": 1727446886, "checkpoint_dir_name": null, "done": false, "training_iteration": 9, "trial_id": "b39b0_00011", "date": "2024-09-27_21-21-26", "time_this_iter_s": 155.07568669319153, "time_total_s": 1312.1282241344452, "pid": 4097730, "hostname": "prism-2.apex.cmkl.ac.th", "node_ip": "172.16.101.112", "config": {"architecture": [64, 128, 256], "lr": 0.0007611817967705463, "batch_size": 30, "num_epochs": 82, "optimizer": "SGD"}, "time_since_restore": 1312.1282241344452, "iterations_since_restore": 9}
{"train_loss": 0.01630625009187497, "val_loss": 0.015492522148415446, "val_psnr": 18.45873584334977, "val_ssim": 0.47204413525511824, "timestamp": 1727447033, "checkpoint_dir_name": null, "done": false, "training_iteration": 10, "trial_id": "b39b0_00011", "date": "2024-09-27_21-23-53", "time_this_iter_s": 147.00589609146118, "time_total_s": 1459.1341202259064, "pid": 4097730, "hostname": "prism-2.apex.cmkl.ac.th", "node_ip": "172.16.101.112", "config": {"architecture": [64, 128, 256], "lr": 0.0007611817967705463, "batch_size": 30, "num_epochs": 82, "optimizer": "SGD"}, "time_since_restore": 1459.1341202259064, "iterations_since_restore": 10}
{"train_loss": 0.015976533201755957, "val_loss": 0.0152070715976879, "val_psnr": 18.541287525224416, "val_ssim": 0.47734231706211966, "timestamp": 1727447180, "checkpoint_dir_name": null, "done": false, "training_iteration": 11, "trial_id": "b39b0_00011", "date": "2024-09-27_21-26-20", "time_this_iter_s": 147.2754726409912, "time_total_s": 1606.4095928668976, "pid": 4097730, "hostname": "prism-2.apex.cmkl.ac.th", "node_ip": "172.16.101.112", "config": {"architecture": [64, 128, 256], "lr": 0.0007611817967705463, "batch_size": 30, "num_epochs": 82, "optimizer": "SGD"}, "time_since_restore": 1606.4095928668976, "iterations_since_restore": 11}
{"train_loss": 0.015999490572139622, "val_loss": 0.014904700205661356, "val_psnr": 18.617944613542914, "val_ssim": 0.48158470733215414, "timestamp": 1727447326, "checkpoint_dir_name": null, "done": false, "training_iteration": 12, "trial_id": "b39b0_00011", "date": "2024-09-27_21-28-46", "time_this_iter_s": 145.7742509841919, "time_total_s": 1752.1838438510895, "pid": 4097730, "hostname": "prism-2.apex.cmkl.ac.th", "node_ip": "172.16.101.112", "config": {"architecture": [64, 128, 256], "lr": 0.0007611817967705463, "batch_size": 30, "num_epochs": 82, "optimizer": "SGD"}, "time_since_restore": 1752.1838438510895, "iterations_since_restore": 12}
{"train_loss": 0.015704459748230874, "val_loss": 0.014853660105727614, "val_psnr": 18.649693086156525, "val_ssim": 0.48638884372015795, "timestamp": 1727447463, "checkpoint_dir_name": null, "done": false, "training_iteration": 13, "trial_id": "b39b0_00011", "date": "2024-09-27_21-31-03", "time_this_iter_s": 136.93688988685608, "time_total_s": 1889.1207337379456, "pid": 4097730, "hostname": "prism-2.apex.cmkl.ac.th", "node_ip": "172.16.101.112", "config": {"architecture": [64, 128, 256], "lr": 0.0007611817967705463, "batch_size": 30, "num_epochs": 82, "optimizer": "SGD"}, "time_since_restore": 1889.1207337379456, "iterations_since_restore": 13}
{"train_loss": 0.015513143377611414, "val_loss": 0.014712378173135221, "val_psnr": 18.6858644802882, "val_ssim": 0.4900028595849872, "timestamp": 1727447610, "checkpoint_dir_name": null, "done": false, "training_iteration": 14, "trial_id": "b39b0_00011", "date": "2024-09-27_21-33-30", "time_this_iter_s": 147.26443481445312, "time_total_s": 2036.3851685523987, "pid": 4097730, "hostname": "prism-2.apex.cmkl.ac.th", "node_ip": "172.16.101.112", "config": {"architecture": [64, 128, 256], "lr": 0.0007611817967705463, "batch_size": 30, "num_epochs": 82, "optimizer": "SGD"}, "time_since_restore": 2036.3851685523987, "iterations_since_restore": 14}
{"train_loss": 0.015440165819600225, "val_loss": 0.014504276416264474, "val_psnr": 18.746575250891482, "val_ssim": 0.4935485209946831, "timestamp": 1727447744, "checkpoint_dir_name": null, "done": false, "training_iteration": 15, "trial_id": "b39b0_00011", "date": "2024-09-27_21-35-44", "time_this_iter_s": 133.16155576705933, "time_total_s": 2169.546724319458, "pid": 4097730, "hostname": "prism-2.apex.cmkl.ac.th", "node_ip": "172.16.101.112", "config": {"architecture": [64, 128, 256], "lr": 0.0007611817967705463, "batch_size": 30, "num_epochs": 82, "optimizer": "SGD"}, "time_since_restore": 2169.546724319458, "iterations_since_restore": 15}
{"train_loss": 0.01534597740508616, "val_loss": 0.014453850099816918, "val_psnr": 18.76454416366953, "val_ssim": 0.49572257433086636, "timestamp": 1727447872, "checkpoint_dir_name": null, "done": false, "training_iteration": 16, "trial_id": "b39b0_00011", "date": "2024-09-27_21-37-52", "time_this_iter_s": 128.03033757209778, "time_total_s": 2297.577061891556, "pid": 4097730, "hostname": "prism-2.apex.cmkl.ac.th", "node_ip": "172.16.101.112", "config": {"architecture": [64, 128, 256], "lr": 0.0007611817967705463, "batch_size": 30, "num_epochs": 82, "optimizer": "SGD"}, "time_since_restore": 2297.577061891556, "iterations_since_restore": 16}
{"train_loss": 0.015391247055958956, "val_loss": 0.01446967616211623, "val_psnr": 18.77828205311835, "val_ssim": 0.500049022714297, "timestamp": 1727448018, "checkpoint_dir_name": null, "done": false, "training_iteration": 17, "trial_id": "b39b0_00011", "date": "2024-09-27_21-40-18", "time_this_iter_s": 146.3985390663147, "time_total_s": 2443.9756009578705, "pid": 4097730, "hostname": "prism-2.apex.cmkl.ac.th", "node_ip": "172.16.101.112", "config": {"architecture": [64, 128, 256], "lr": 0.0007611817967705463, "batch_size": 30, "num_epochs": 82, "optimizer": "SGD"}, "time_since_restore": 2443.9756009578705, "iterations_since_restore": 17}
{"train_loss": 0.015067598894238471, "val_loss": 0.014168229959905148, "val_psnr": 18.850684142663024, "val_ssim": 0.501464911746482, "timestamp": 1727448167, "checkpoint_dir_name": null, "done": false, "training_iteration": 18, "trial_id": "b39b0_00011", "date": "2024-09-27_21-42-47", "time_this_iter_s": 149.3898947238922, "time_total_s": 2593.3654956817627, "pid": 4097730, "hostname": "prism-2.apex.cmkl.ac.th", "node_ip": "172.16.101.112", "config": {"architecture": [64, 128, 256], "lr": 0.0007611817967705463, "batch_size": 30, "num_epochs": 82, "optimizer": "SGD"}, "time_since_restore": 2593.3654956817627, "iterations_since_restore": 18}
{"train_loss": 0.014981160230236127, "val_loss": 0.014199708150699734, "val_psnr": 18.85968982208085, "val_ssim": 0.5036716455717881, "timestamp": 1727448322, "checkpoint_dir_name": null, "done": false, "training_iteration": 19, "trial_id": "b39b0_00011", "date": "2024-09-27_21-45-22", "time_this_iter_s": 154.1475636959076, "time_total_s": 2747.5130593776703, "pid": 4097730, "hostname": "prism-2.apex.cmkl.ac.th", "node_ip": "172.16.101.112", "config": {"architecture": [64, 128, 256], "lr": 0.0007611817967705463, "batch_size": 30, "num_epochs": 82, "optimizer": "SGD"}, "time_since_restore": 2747.5130593776703, "iterations_since_restore": 19}
{"train_loss": 0.01486319681047462, "val_loss": 0.01411972320638597, "val_psnr": 18.888172542967272, "val_ssim": 0.5069666647935908, "timestamp": 1727448463, "checkpoint_dir_name": null, "done": false, "training_iteration": 20, "trial_id": "b39b0_00011", "date": "2024-09-27_21-47-43", "time_this_iter_s": 141.63559889793396, "time_total_s": 2889.1486582756042, "pid": 4097730, "hostname": "prism-2.apex.cmkl.ac.th", "node_ip": "172.16.101.112", "config": {"architecture": [64, 128, 256], "lr": 0.0007611817967705463, "batch_size": 30, "num_epochs": 82, "optimizer": "SGD"}, "time_since_restore": 2889.1486582756042, "iterations_since_restore": 20}
{"train_loss": 0.014851698172278702, "val_loss": 0.014066413203254342, "val_psnr": 18.899288162148206, "val_ssim": 0.5079285788089037, "timestamp": 1727448611, "checkpoint_dir_name": null, "done": false, "training_iteration": 21, "trial_id": "b39b0_00011", "date": "2024-09-27_21-50-11", "time_this_iter_s": 147.24483942985535, "time_total_s": 3036.3934977054596, "pid": 4097730, "hostname": "prism-2.apex.cmkl.ac.th", "node_ip": "172.16.101.112", "config": {"architecture": [64, 128, 256], "lr": 0.0007611817967705463, "batch_size": 30, "num_epochs": 82, "optimizer": "SGD"}, "time_since_restore": 3036.3934977054596, "iterations_since_restore": 21}
{"train_loss": 0.014737844507908448, "val_loss": 0.01399533168412745, "val_psnr": 18.93938151219908, "val_ssim": 0.51131504868716, "timestamp": 1727448783, "checkpoint_dir_name": null, "done": false, "training_iteration": 22, "trial_id": "b39b0_00011", "date": "2024-09-27_21-53-03", "time_this_iter_s": 172.43249082565308, "time_total_s": 3208.8259885311127, "pid": 4097730, "hostname": "prism-2.apex.cmkl.ac.th", "node_ip": "172.16.101.112", "config": {"architecture": [64, 128, 256], "lr": 0.0007611817967705463, "batch_size": 30, "num_epochs": 82, "optimizer": "SGD"}, "time_since_restore": 3208.8259885311127, "iterations_since_restore": 22}
{"train_loss": 0.014774577068164945, "val_loss": 0.013844152600504457, "val_psnr": 18.97520920233407, "val_ssim": 0.5122327106073499, "timestamp": 1727448928, "checkpoint_dir_name": null, "done": false, "training_iteration": 23, "trial_id": "b39b0_00011", "date": "2024-09-27_21-55-28", "time_this_iter_s": 144.82754158973694, "time_total_s": 3353.6535301208496, "pid": 4097730, "hostname": "prism-2.apex.cmkl.ac.th", "node_ip": "172.16.101.112", "config": {"architecture": [64, 128, 256], "lr": 0.0007611817967705463, "batch_size": 30, "num_epochs": 82, "optimizer": "SGD"}, "time_since_restore": 3353.6535301208496, "iterations_since_restore": 23}
{"train_loss": 0.014606390489498154, "val_loss": 0.01365441172849387, "val_psnr": 19.018094164681067, "val_ssim": 0.5144013388678431, "timestamp": 1727449072, "checkpoint_dir_name": null, "done": false, "training_iteration": 24, "trial_id": "b39b0_00011", "date": "2024-09-27_21-57-52", "time_this_iter_s": 143.97396874427795, "time_total_s": 3497.6274988651276, "pid": 4097730, "hostname": "prism-2.apex.cmkl.ac.th", "node_ip": "172.16.101.112", "config": {"architecture": [64, 128, 256], "lr": 0.0007611817967705463, "batch_size": 30, "num_epochs": 82, "optimizer": "SGD"}, "time_since_restore": 3497.6274988651276, "iterations_since_restore": 24}
{"train_loss": 0.014598193514393643, "val_loss": 0.013720809486694635, "val_psnr": 19.003108324137816, "val_ssim": 0.5150734818975131, "timestamp": 1727449220, "checkpoint_dir_name": null, "done": false, "training_iteration": 25, "trial_id": "b39b0_00011", "date": "2024-09-27_22-00-20", "time_this_iter_s": 147.86552238464355, "time_total_s": 3645.493021249771, "pid": 4097730, "hostname": "prism-2.apex.cmkl.ac.th", "node_ip": "172.16.101.112", "config": {"architecture": [64, 128, 256], "lr": 0.0007611817967705463, "batch_size": 30, "num_epochs": 82, "optimizer": "SGD"}, "time_since_restore": 3645.493021249771, "iterations_since_restore": 25}
{"train_loss": 0.014520682430593297, "val_loss": 0.013642048672772944, "val_psnr": 19.046442524562476, "val_ssim": 0.5177408435493708, "timestamp": 1727449368, "checkpoint_dir_name": null, "done": false, "training_iteration": 26, "trial_id": "b39b0_00011", "date": "2024-09-27_22-02-48", "time_this_iter_s": 148.14654994010925, "time_total_s": 3793.6395711898804, "pid": 4097730, "hostname": "prism-2.apex.cmkl.ac.th", "node_ip": "172.16.101.112", "config": {"architecture": [64, 128, 256], "lr": 0.0007611817967705463, "batch_size": 30, "num_epochs": 82, "optimizer": "SGD"}, "time_since_restore": 3793.6395711898804, "iterations_since_restore": 26}
{"train_loss": 0.01448999747633934, "val_loss": 0.01354554831981659, "val_psnr": 19.05811097107653, "val_ssim": 0.5187333132103086, "timestamp": 1727449518, "checkpoint_dir_name": null, "done": false, "training_iteration": 27, "trial_id": "b39b0_00011", "date": "2024-09-27_22-05-18", "time_this_iter_s": 149.9765501022339, "time_total_s": 3943.6161212921143, "pid": 4097730, "hostname": "prism-2.apex.cmkl.ac.th", "node_ip": "172.16.101.112", "config": {"architecture": [64, 128, 256], "lr": 0.0007611817967705463, "batch_size": 30, "num_epochs": 82, "optimizer": "SGD"}, "time_since_restore": 3943.6161212921143, "iterations_since_restore": 27}
{"train_loss": 0.014389913567574695, "val_loss": 0.01349405883345753, "val_psnr": 19.082348551229053, "val_ssim": 0.5205668656229973, "timestamp": 1727449663, "checkpoint_dir_name": null, "done": false, "training_iteration": 28, "trial_id": "b39b0_00011", "date": "2024-09-27_22-07-43", "time_this_iter_s": 145.37154817581177, "time_total_s": 4088.987669467926, "pid": 4097730, "hostname": "prism-2.apex.cmkl.ac.th", "node_ip": "172.16.101.112", "config": {"architecture": [64, 128, 256], "lr": 0.0007611817967705463, "batch_size": 30, "num_epochs": 82, "optimizer": "SGD"}, "time_since_restore": 4088.987669467926, "iterations_since_restore": 28}
{"train_loss": 0.014372437676647677, "val_loss": 0.013531877445057034, "val_psnr": 19.072132136045447, "val_ssim": 0.5210999224533638, "timestamp": 1727449816, "checkpoint_dir_name": null, "done": false, "training_iteration": 29, "trial_id": "b39b0_00011", "date": "2024-09-27_22-10-16", "time_this_iter_s": 152.3889353275299, "time_total_s": 4241.376604795456, "pid": 4097730, "hostname": "prism-2.apex.cmkl.ac.th", "node_ip": "172.16.101.112", "config": {"architecture": [64, 128, 256], "lr": 0.0007611817967705463, "batch_size": 30, "num_epochs": 82, "optimizer": "SGD"}, "time_since_restore": 4241.376604795456, "iterations_since_restore": 29}
{"train_loss": 0.014182115896837787, "val_loss": 0.013326837746426463, "val_psnr": 19.13234543669236, "val_ssim": 0.5232870201344292, "timestamp": 1727449957, "checkpoint_dir_name": null, "done": false, "training_iteration": 30, "trial_id": "b39b0_00011", "date": "2024-09-27_22-12-37", "time_this_iter_s": 141.40873003005981, "time_total_s": 4382.785334825516, "pid": 4097730, "hostname": "prism-2.apex.cmkl.ac.th", "node_ip": "172.16.101.112", "config": {"architecture": [64, 128, 256], "lr": 0.0007611817967705463, "batch_size": 30, "num_epochs": 82, "optimizer": "SGD"}, "time_since_restore": 4382.785334825516, "iterations_since_restore": 30}
{"train_loss": 0.014282807334093378, "val_loss": 0.013494576714001595, "val_psnr": 19.08665070403847, "val_ssim": 0.5233078177198768, "timestamp": 1727450108, "checkpoint_dir_name": null, "done": false, "training_iteration": 31, "trial_id": "b39b0_00011", "date": "2024-09-27_22-15-08", "time_this_iter_s": 151.40249276161194, "time_total_s": 4534.187827587128, "pid": 4097730, "hostname": "prism-2.apex.cmkl.ac.th", "node_ip": "172.16.101.112", "config": {"architecture": [64, 128, 256], "lr": 0.0007611817967705463, "batch_size": 30, "num_epochs": 82, "optimizer": "SGD"}, "time_since_restore": 4534.187827587128, "iterations_since_restore": 31}
{"train_loss": 0.014235715528484435, "val_loss": 0.013384309611283243, "val_psnr": 19.121510323855528, "val_ssim": 0.524247437166671, "timestamp": 1727450258, "checkpoint_dir_name": null, "done": false, "training_iteration": 32, "trial_id": "b39b0_00011", "date": "2024-09-27_22-17-38", "time_this_iter_s": 149.68330788612366, "time_total_s": 4683.871135473251, "pid": 4097730, "hostname": "prism-2.apex.cmkl.ac.th", "node_ip": "172.16.101.112", "config": {"architecture": [64, 128, 256], "lr": 0.0007611817967705463, "batch_size": 30, "num_epochs": 82, "optimizer": "SGD"}, "time_since_restore": 4683.871135473251, "iterations_since_restore": 32}
{"train_loss": 0.01416278349235654, "val_loss": 0.013360104677267372, "val_psnr": 19.13238873860458, "val_ssim": 0.5245387326106429, "timestamp": 1727450406, "checkpoint_dir_name": null, "done": false, "training_iteration": 33, "trial_id": "b39b0_00011", "date": "2024-09-27_22-20-06", "time_this_iter_s": 147.50678539276123, "time_total_s": 4831.377920866013, "pid": 4097730, "hostname": "prism-2.apex.cmkl.ac.th", "node_ip": "172.16.101.112", "config": {"architecture": [64, 128, 256], "lr": 0.0007611817967705463, "batch_size": 30, "num_epochs": 82, "optimizer": "SGD"}, "time_since_restore": 4831.377920866013, "iterations_since_restore": 33}
{"train_loss": 0.014133785242447629, "val_loss": 0.013409369592554867, "val_psnr": 19.1136557053975, "val_ssim": 0.5264976095954577, "timestamp": 1727450583, "checkpoint_dir_name": null, "done": false, "training_iteration": 34, "trial_id": "b39b0_00011", "date": "2024-09-27_22-23-03", "time_this_iter_s": 177.3299400806427, "time_total_s": 5008.707860946655, "pid": 4097730, "hostname": "prism-2.apex.cmkl.ac.th", "node_ip": "172.16.101.112", "config": {"architecture": [64, 128, 256], "lr": 0.0007611817967705463, "batch_size": 30, "num_epochs": 82, "optimizer": "SGD"}, "time_since_restore": 5008.707860946655, "iterations_since_restore": 34}
{"train_loss": 0.014115909966640174, "val_loss": 0.013345026527531445, "val_psnr": 19.12341298628029, "val_ssim": 0.5258608447040121, "timestamp": 1727450741, "checkpoint_dir_name": null, "done": false, "training_iteration": 35, "trial_id": "b39b0_00011", "date": "2024-09-27_22-25-41", "time_this_iter_s": 157.77127408981323, "time_total_s": 5166.4791350364685, "pid": 4097730, "hostname": "prism-2.apex.cmkl.ac.th", "node_ip": "172.16.101.112", "config": {"architecture": [64, 128, 256], "lr": 0.0007611817967705463, "batch_size": 30, "num_epochs": 82, "optimizer": "SGD"}, "time_since_restore": 5166.4791350364685, "iterations_since_restore": 35}
{"train_loss": 0.014030747554497793, "val_loss": 0.01321575466543436, "val_psnr": 19.179364004886352, "val_ssim": 0.5286480425149203, "timestamp": 1727450890, "checkpoint_dir_name": null, "done": false, "training_iteration": 36, "trial_id": "b39b0_00011", "date": "2024-09-27_22-28-10", "time_this_iter_s": 149.34718418121338, "time_total_s": 5315.826319217682, "pid": 4097730, "hostname": "prism-2.apex.cmkl.ac.th", "node_ip": "172.16.101.112", "config": {"architecture": [64, 128, 256], "lr": 0.0007611817967705463, "batch_size": 30, "num_epochs": 82, "optimizer": "SGD"}, "time_since_restore": 5315.826319217682, "iterations_since_restore": 36}
{"train_loss": 0.014049489136086777, "val_loss": 0.013184017036110163, "val_psnr": 19.1842973279753, "val_ssim": 0.5293583455284436, "timestamp": 1727451043, "checkpoint_dir_name": null, "done": false, "training_iteration": 37, "trial_id": "b39b0_00011", "date": "2024-09-27_22-30-43", "time_this_iter_s": 153.08426928520203, "time_total_s": 5468.910588502884, "pid": 4097730, "hostname": "prism-2.apex.cmkl.ac.th", "node_ip": "172.16.101.112", "config": {"architecture": [64, 128, 256], "lr": 0.0007611817967705463, "batch_size": 30, "num_epochs": 82, "optimizer": "SGD"}, "time_since_restore": 5468.910588502884, "iterations_since_restore": 37}
{"train_loss": 0.014043737960746512, "val_loss": 0.013249828908592463, "val_psnr": 19.16989553856445, "val_ssim": 0.5299511806219817, "timestamp": 1727451195, "checkpoint_dir_name": null, "done": false, "training_iteration": 38, "trial_id": "b39b0_00011", "date": "2024-09-27_22-33-15", "time_this_iter_s": 151.71925020217896, "time_total_s": 5620.629838705063, "pid": 4097730, "hostname": "prism-2.apex.cmkl.ac.th", "node_ip": "172.16.101.112", "config": {"architecture": [64, 128, 256], "lr": 0.0007611817967705463, "batch_size": 30, "num_epochs": 82, "optimizer": "SGD"}, "time_since_restore": 5620.629838705063, "iterations_since_restore": 38}
{"train_loss": 0.014034567257622256, "val_loss": 0.013159187422133982, "val_psnr": 19.205163072639728, "val_ssim": 0.5307599622259538, "timestamp": 1727451352, "checkpoint_dir_name": null, "done": false, "training_iteration": 39, "trial_id": "b39b0_00011", "date": "2024-09-27_22-35-52", "time_this_iter_s": 156.54733180999756, "time_total_s": 5777.17717051506, "pid": 4097730, "hostname": "prism-2.apex.cmkl.ac.th", "node_ip": "172.16.101.112", "config": {"architecture": [64, 128, 256], "lr": 0.0007611817967705463, "batch_size": 30, "num_epochs": 82, "optimizer": "SGD"}, "time_since_restore": 5777.17717051506, "iterations_since_restore": 39}
{"train_loss": 0.013959968072595075, "val_loss": 0.013174848700873553, "val_psnr": 19.198005773962887, "val_ssim": 0.531560021477441, "timestamp": 1727451493, "checkpoint_dir_name": null, "done": false, "training_iteration": 40, "trial_id": "b39b0_00011", "date": "2024-09-27_22-38-13", "time_this_iter_s": 141.2740135192871, "time_total_s": 5918.4511840343475, "pid": 4097730, "hostname": "prism-2.apex.cmkl.ac.th", "node_ip": "172.16.101.112", "config": {"architecture": [64, 128, 256], "lr": 0.0007611817967705463, "batch_size": 30, "num_epochs": 82, "optimizer": "SGD"}, "time_since_restore": 5918.4511840343475, "iterations_since_restore": 40}
{"train_loss": 0.01389630397898145, "val_loss": 0.013197756209410726, "val_psnr": 19.187526100221596, "val_ssim": 0.5322459416488806, "timestamp": 1727451648, "checkpoint_dir_name": null, "done": false, "training_iteration": 41, "trial_id": "b39b0_00011", "date": "2024-09-27_22-40-48", "time_this_iter_s": 155.23292350769043, "time_total_s": 6073.684107542038, "pid": 4097730, "hostname": "prism-2.apex.cmkl.ac.th", "node_ip": "172.16.101.112", "config": {"architecture": [64, 128, 256], "lr": 0.0007611817967705463, "batch_size": 30, "num_epochs": 82, "optimizer": "SGD"}, "time_since_restore": 6073.684107542038, "iterations_since_restore": 41}
{"train_loss": 0.01378405626048334, "val_loss": 0.012941052210517228, "val_psnr": 19.26410817713499, "val_ssim": 0.5335273158674438, "timestamp": 1727451791, "checkpoint_dir_name": null, "done": false, "training_iteration": 42, "trial_id": "b39b0_00011", "date": "2024-09-27_22-43-11", "time_this_iter_s": 142.57076573371887, "time_total_s": 6216.254873275757, "pid": 4097730, "hostname": "prism-2.apex.cmkl.ac.th", "node_ip": "172.16.101.112", "config": {"architecture": [64, 128, 256], "lr": 0.0007611817967705463, "batch_size": 30, "num_epochs": 82, "optimizer": "SGD"}, "time_since_restore": 6216.254873275757, "iterations_since_restore": 42}
{"train_loss": 0.013828305214410648, "val_loss": 0.012911753016524016, "val_psnr": 19.28188070031257, "val_ssim": 0.5355902842109402, "timestamp": 1727451930, "checkpoint_dir_name": null, "done": false, "training_iteration": 43, "trial_id": "b39b0_00011", "date": "2024-09-27_22-45-30", "time_this_iter_s": 139.75654125213623, "time_total_s": 6356.011414527893, "pid": 4097730, "hostname": "prism-2.apex.cmkl.ac.th", "node_ip": "172.16.101.112", "config": {"architecture": [64, 128, 256], "lr": 0.0007611817967705463, "batch_size": 30, "num_epochs": 82, "optimizer": "SGD"}, "time_since_restore": 6356.011414527893, "iterations_since_restore": 43}
{"train_loss": 0.013830490943510085, "val_loss": 0.012980513013899327, "val_psnr": 19.2529158350949, "val_ssim": 0.5341853772625327, "timestamp": 1727452058, "checkpoint_dir_name": null, "done": false, "training_iteration": 44, "trial_id": "b39b0_00011", "date": "2024-09-27_22-47-38", "time_this_iter_s": 127.06537580490112, "time_total_s": 6483.076790332794, "pid": 4097730, "hostname": "prism-2.apex.cmkl.ac.th", "node_ip": "172.16.101.112", "config": {"architecture": [64, 128, 256], "lr": 0.0007611817967705463, "batch_size": 30, "num_epochs": 82, "optimizer": "SGD"}, "time_since_restore": 6483.076790332794, "iterations_since_restore": 44}
{"train_loss": 0.013921226895181462, "val_loss": 0.012977681877091527, "val_psnr": 19.256779858761675, "val_ssim": 0.5352045595844587, "timestamp": 1727452185, "checkpoint_dir_name": null, "done": false, "training_iteration": 45, "trial_id": "b39b0_00011", "date": "2024-09-27_22-49-45", "time_this_iter_s": 127.31050300598145, "time_total_s": 6610.387293338776, "pid": 4097730, "hostname": "prism-2.apex.cmkl.ac.th", "node_ip": "172.16.101.112", "config": {"architecture": [64, 128, 256], "lr": 0.0007611817967705463, "batch_size": 30, "num_epochs": 82, "optimizer": "SGD"}, "time_since_restore": 6610.387293338776, "iterations_since_restore": 45}
{"train_loss": 0.01380307283718139, "val_loss": 0.013092171344906091, "val_psnr": 19.224977344054025, "val_ssim": 0.5356090705320239, "timestamp": 1727452311, "checkpoint_dir_name": null, "done": false, "training_iteration": 46, "trial_id": "b39b0_00011", "date": "2024-09-27_22-51-51", "time_this_iter_s": 126.32815027236938, "time_total_s": 6736.715443611145, "pid": 4097730, "hostname": "prism-2.apex.cmkl.ac.th", "node_ip": "172.16.101.112", "config": {"architecture": [64, 128, 256], "lr": 0.0007611817967705463, "batch_size": 30, "num_epochs": 82, "optimizer": "SGD"}, "time_since_restore": 6736.715443611145, "iterations_since_restore": 46}
{"train_loss": 0.013665854055434466, "val_loss": 0.012956347009167075, "val_psnr": 19.27363388585955, "val_ssim": 0.5368786732628942, "timestamp": 1727452452, "checkpoint_dir_name": null, "done": false, "training_iteration": 47, "trial_id": "b39b0_00011", "date": "2024-09-27_22-54-12", "time_this_iter_s": 140.49792766571045, "time_total_s": 6877.2133712768555, "pid": 4097730, "hostname": "prism-2.apex.cmkl.ac.th", "node_ip": "172.16.101.112", "config": {"architecture": [64, 128, 256], "lr": 0.0007611817967705463, "batch_size": 30, "num_epochs": 82, "optimizer": "SGD"}, "time_since_restore": 6877.2133712768555, "iterations_since_restore": 47}
{"train_loss": 0.01361906765261665, "val_loss": 0.012915863660164178, "val_psnr": 19.282690748179316, "val_ssim": 0.5367860749587416, "timestamp": 1727452582, "checkpoint_dir_name": null, "done": false, "training_iteration": 48, "trial_id": "b39b0_00011", "date": "2024-09-27_22-56-22", "time_this_iter_s": 130.52499389648438, "time_total_s": 7007.73836517334, "pid": 4097730, "hostname": "prism-2.apex.cmkl.ac.th", "node_ip": "172.16.101.112", "config": {"architecture": [64, 128, 256], "lr": 0.0007611817967705463, "batch_size": 30, "num_epochs": 82, "optimizer": "SGD"}, "time_since_restore": 7007.73836517334, "iterations_since_restore": 48}
{"train_loss": 0.013742756472202017, "val_loss": 0.012795889987610281, "val_psnr": 19.31636029487742, "val_ssim": 0.5381225949476163, "timestamp": 1727452712, "checkpoint_dir_name": null, "done": false, "training_iteration": 49, "trial_id": "b39b0_00011", "date": "2024-09-27_22-58-32", "time_this_iter_s": 130.07552790641785, "time_total_s": 7137.813893079758, "pid": 4097730, "hostname": "prism-2.apex.cmkl.ac.th", "node_ip": "172.16.101.112", "config": {"architecture": [64, 128, 256], "lr": 0.0007611817967705463, "batch_size": 30, "num_epochs": 82, "optimizer": "SGD"}, "time_since_restore": 7137.813893079758, "iterations_since_restore": 49}
{"train_loss": 0.013709590758662672, "val_loss": 0.012770838998258115, "val_psnr": 19.324120207692566, "val_ssim": 0.5385260033011436, "timestamp": 1727452841, "checkpoint_dir_name": null, "done": false, "training_iteration": 50, "trial_id": "b39b0_00011", "date": "2024-09-27_23-00-41", "time_this_iter_s": 128.67983722686768, "time_total_s": 7266.493730306625, "pid": 4097730, "hostname": "prism-2.apex.cmkl.ac.th", "node_ip": "172.16.101.112", "config": {"architecture": [64, 128, 256], "lr": 0.0007611817967705463, "batch_size": 30, "num_epochs": 82, "optimizer": "SGD"}, "time_since_restore": 7266.493730306625, "iterations_since_restore": 50}
{"train_loss": 0.013685479859123006, "val_loss": 0.012904676357284189, "val_psnr": 19.28609314335228, "val_ssim": 0.5380430274531245, "timestamp": 1727452988, "checkpoint_dir_name": null, "done": false, "training_iteration": 51, "trial_id": "b39b0_00011", "date": "2024-09-27_23-03-08", "time_this_iter_s": 147.011470079422, "time_total_s": 7413.505200386047, "pid": 4097730, "hostname": "prism-2.apex.cmkl.ac.th", "node_ip": "172.16.101.112", "config": {"architecture": [64, 128, 256], "lr": 0.0007611817967705463, "batch_size": 30, "num_epochs": 82, "optimizer": "SGD"}, "time_since_restore": 7413.505200386047, "iterations_since_restore": 51}
{"train_loss": 0.013623262631008402, "val_loss": 0.012681237864308059, "val_psnr": 19.358765140791654, "val_ssim": 0.5393222648079197, "timestamp": 1727453133, "checkpoint_dir_name": null, "done": false, "training_iteration": 52, "trial_id": "b39b0_00011", "date": "2024-09-27_23-05-33", "time_this_iter_s": 145.27890276908875, "time_total_s": 7558.784103155136, "pid": 4097730, "hostname": "prism-2.apex.cmkl.ac.th", "node_ip": "172.16.101.112", "config": {"architecture": [64, 128, 256], "lr": 0.0007611817967705463, "batch_size": 30, "num_epochs": 82, "optimizer": "SGD"}, "time_since_restore": 7558.784103155136, "iterations_since_restore": 52}
{"train_loss": 0.013578227445250377, "val_loss": 0.012881752513349056, "val_psnr": 19.300881068061663, "val_ssim": 0.5399092279151082, "timestamp": 1727453286, "checkpoint_dir_name": null, "done": false, "training_iteration": 53, "trial_id": "b39b0_00011", "date": "2024-09-27_23-08-06", "time_this_iter_s": 152.4402620792389, "time_total_s": 7711.224365234375, "pid": 4097730, "hostname": "prism-2.apex.cmkl.ac.th", "node_ip": "172.16.101.112", "config": {"architecture": [64, 128, 256], "lr": 0.0007611817967705463, "batch_size": 30, "num_epochs": 82, "optimizer": "SGD"}, "time_since_restore": 7711.224365234375, "iterations_since_restore": 53}
{"train_loss": 0.013575042333686725, "val_loss": 0.012770169321447611, "val_psnr": 19.336446620167294, "val_ssim": 0.5413425984531641, "timestamp": 1727453429, "checkpoint_dir_name": null, "done": false, "training_iteration": 54, "trial_id": "b39b0_00011", "date": "2024-09-27_23-10-29", "time_this_iter_s": 143.115620136261, "time_total_s": 7854.339985370636, "pid": 4097730, "hostname": "prism-2.apex.cmkl.ac.th", "node_ip": "172.16.101.112", "config": {"architecture": [64, 128, 256], "lr": 0.0007611817967705463, "batch_size": 30, "num_epochs": 82, "optimizer": "SGD"}, "time_since_restore": 7854.339985370636, "iterations_since_restore": 54}
{"train_loss": 0.01364779255585745, "val_loss": 0.012795173320919275, "val_psnr": 19.333450136804483, "val_ssim": 0.5415381789728999, "timestamp": 1727453567, "checkpoint_dir_name": null, "done": false, "training_iteration": 55, "trial_id": "b39b0_00011", "date": "2024-09-27_23-12-47", "time_this_iter_s": 137.84728956222534, "time_total_s": 7992.187274932861, "pid": 4097730, "hostname": "prism-2.apex.cmkl.ac.th", "node_ip": "172.16.101.112", "config": {"architecture": [64, 128, 256], "lr": 0.0007611817967705463, "batch_size": 30, "num_epochs": 82, "optimizer": "SGD"}, "time_since_restore": 7992.187274932861, "iterations_since_restore": 55}
{"train_loss": 0.013467569830827414, "val_loss": 0.012850354383699596, "val_psnr": 19.308853641082628, "val_ssim": 0.5410436599602302, "timestamp": 1727453725, "checkpoint_dir_name": null, "done": false, "training_iteration": 56, "trial_id": "b39b0_00011", "date": "2024-09-27_23-15-25", "time_this_iter_s": 157.8826243877411, "time_total_s": 8150.069899320602, "pid": 4097730, "hostname": "prism-2.apex.cmkl.ac.th", "node_ip": "172.16.101.112", "config": {"architecture": [64, 128, 256], "lr": 0.0007611817967705463, "batch_size": 30, "num_epochs": 82, "optimizer": "SGD"}, "time_since_restore": 8150.069899320602, "iterations_since_restore": 56}
{"train_loss": 0.013506214845692739, "val_loss": 0.012733946330845356, "val_psnr": 19.344569925916566, "val_ssim": 0.5427292811622222, "timestamp": 1727453864, "checkpoint_dir_name": null, "done": false, "training_iteration": 57, "trial_id": "b39b0_00011", "date": "2024-09-27_23-17-44", "time_this_iter_s": 139.2146019935608, "time_total_s": 8289.284501314163, "pid": 4097730, "hostname": "prism-2.apex.cmkl.ac.th", "node_ip": "172.16.101.112", "config": {"architecture": [64, 128, 256], "lr": 0.0007611817967705463, "batch_size": 30, "num_epochs": 82, "optimizer": "SGD"}, "time_since_restore": 8289.284501314163, "iterations_since_restore": 57}
{"train_loss": 0.013502780015114695, "val_loss": 0.012746028979308903, "val_psnr": 19.336760133160677, "val_ssim": 0.5419750340779622, "timestamp": 1727454010, "checkpoint_dir_name": null, "done": false, "training_iteration": 58, "trial_id": "b39b0_00011", "date": "2024-09-27_23-20-10", "time_this_iter_s": 145.76940608024597, "time_total_s": 8435.05390739441, "pid": 4097730, "hostname": "prism-2.apex.cmkl.ac.th", "node_ip": "172.16.101.112", "config": {"architecture": [64, 128, 256], "lr": 0.0007611817967705463, "batch_size": 30, "num_epochs": 82, "optimizer": "SGD"}, "time_since_restore": 8435.05390739441, "iterations_since_restore": 58}
{"train_loss": 0.013497698527062311, "val_loss": 0.012631316776387394, "val_psnr": 19.366636188404254, "val_ssim": 0.5425577511563897, "timestamp": 1727454150, "checkpoint_dir_name": null, "done": false, "training_iteration": 59, "trial_id": "b39b0_00011", "date": "2024-09-27_23-22-30", "time_this_iter_s": 140.6045482158661, "time_total_s": 8575.658455610275, "pid": 4097730, "hostname": "prism-2.apex.cmkl.ac.th", "node_ip": "172.16.101.112", "config": {"architecture": [64, 128, 256], "lr": 0.0007611817967705463, "batch_size": 30, "num_epochs": 82, "optimizer": "SGD"}, "time_since_restore": 8575.658455610275, "iterations_since_restore": 59}
{"train_loss": 0.01342528342618607, "val_loss": 0.012699453881941736, "val_psnr": 19.344036349509633, "val_ssim": 0.5415518159394462, "timestamp": 1727454310, "checkpoint_dir_name": null, "done": false, "training_iteration": 60, "trial_id": "b39b0_00011", "date": "2024-09-27_23-25-10", "time_this_iter_s": 159.3020396232605, "time_total_s": 8734.960495233536, "pid": 4097730, "hostname": "prism-2.apex.cmkl.ac.th", "node_ip": "172.16.101.112", "config": {"architecture": [64, 128, 256], "lr": 0.0007611817967705463, "batch_size": 30, "num_epochs": 82, "optimizer": "SGD"}, "time_since_restore": 8734.960495233536, "iterations_since_restore": 60}
{"train_loss": 0.013437204316724093, "val_loss": 0.012592427204363049, "val_psnr": 19.39628963248221, "val_ssim": 0.5436495964725813, "timestamp": 1727454465, "checkpoint_dir_name": null, "done": false, "training_iteration": 61, "trial_id": "b39b0_00011", "date": "2024-09-27_23-27-45", "time_this_iter_s": 155.41841340065002, "time_total_s": 8890.378908634186, "pid": 4097730, "hostname": "prism-2.apex.cmkl.ac.th", "node_ip": "172.16.101.112", "config": {"architecture": [64, 128, 256], "lr": 0.0007611817967705463, "batch_size": 30, "num_epochs": 82, "optimizer": "SGD"}, "time_since_restore": 8890.378908634186, "iterations_since_restore": 61}
{"train_loss": 0.01339978989562951, "val_loss": 0.012669387683272361, "val_psnr": 19.366081379935903, "val_ssim": 0.5437170995622873, "timestamp": 1727454607, "checkpoint_dir_name": null, "done": false, "training_iteration": 62, "trial_id": "b39b0_00011", "date": "2024-09-27_23-30-07", "time_this_iter_s": 141.41828203201294, "time_total_s": 9031.797190666199, "pid": 4097730, "hostname": "prism-2.apex.cmkl.ac.th", "node_ip": "172.16.101.112", "config": {"architecture": [64, 128, 256], "lr": 0.0007611817967705463, "batch_size": 30, "num_epochs": 82, "optimizer": "SGD"}, "time_since_restore": 9031.797190666199, "iterations_since_restore": 62}
{"train_loss": 0.013429342877352611, "val_loss": 0.012570317625068128, "val_psnr": 19.387074367503722, "val_ssim": 0.5434830097109079, "timestamp": 1727454763, "checkpoint_dir_name": null, "done": false, "training_iteration": 63, "trial_id": "b39b0_00011", "date": "2024-09-27_23-32-43", "time_this_iter_s": 156.4461269378662, "time_total_s": 9188.243317604065, "pid": 4097730, "hostname": "prism-2.apex.cmkl.ac.th", "node_ip": "172.16.101.112", "config": {"architecture": [64, 128, 256], "lr": 0.0007611817967705463, "batch_size": 30, "num_epochs": 82, "optimizer": "SGD"}, "time_since_restore": 9188.243317604065, "iterations_since_restore": 63}
{"train_loss": 0.013372675318969414, "val_loss": 0.012639995506033301, "val_psnr": 19.3788762929395, "val_ssim": 0.5446065640151501, "timestamp": 1727454912, "checkpoint_dir_name": null, "done": false, "training_iteration": 64, "trial_id": "b39b0_00011", "date": "2024-09-27_23-35-12", "time_this_iter_s": 148.78444838523865, "time_total_s": 9337.027765989304, "pid": 4097730, "hostname": "prism-2.apex.cmkl.ac.th", "node_ip": "172.16.101.112", "config": {"architecture": [64, 128, 256], "lr": 0.0007611817967705463, "batch_size": 30, "num_epochs": 82, "optimizer": "SGD"}, "time_since_restore": 9337.027765989304, "iterations_since_restore": 64}
{"train_loss": 0.013337393463589252, "val_loss": 0.012586345407180488, "val_psnr": 19.406519550163324, "val_ssim": 0.5456781568204363, "timestamp": 1727455062, "checkpoint_dir_name": null, "done": false, "training_iteration": 65, "trial_id": "b39b0_00011", "date": "2024-09-27_23-37-42", "time_this_iter_s": 150.01684165000916, "time_total_s": 9487.044607639313, "pid": 4097730, "hostname": "prism-2.apex.cmkl.ac.th", "node_ip": "172.16.101.112", "config": {"architecture": [64, 128, 256], "lr": 0.0007611817967705463, "batch_size": 30, "num_epochs": 82, "optimizer": "SGD"}, "time_since_restore": 9487.044607639313, "iterations_since_restore": 65}
{"train_loss": 0.013337626357097178, "val_loss": 0.012497356431558727, "val_psnr": 19.43600550620972, "val_ssim": 0.5462886791303754, "timestamp": 1727455207, "checkpoint_dir_name": null, "done": false, "training_iteration": 66, "trial_id": "b39b0_00011", "date": "2024-09-27_23-40-07", "time_this_iter_s": 145.30535769462585, "time_total_s": 9632.349965333939, "pid": 4097730, "hostname": "prism-2.apex.cmkl.ac.th", "node_ip": "172.16.101.112", "config": {"architecture": [64, 128, 256], "lr": 0.0007611817967705463, "batch_size": 30, "num_epochs": 82, "optimizer": "SGD"}, "time_since_restore": 9632.349965333939, "iterations_since_restore": 66}
{"train_loss": 0.013337366560008376, "val_loss": 0.012525516566820443, "val_psnr": 19.443166910141734, "val_ssim": 0.5470052599882086, "timestamp": 1727455351, "checkpoint_dir_name": null, "done": false, "training_iteration": 67, "trial_id": "b39b0_00011", "date": "2024-09-27_23-42-31", "time_this_iter_s": 144.11353969573975, "time_total_s": 9776.463505029678, "pid": 4097730, "hostname": "prism-2.apex.cmkl.ac.th", "node_ip": "172.16.101.112", "config": {"architecture": [64, 128, 256], "lr": 0.0007611817967705463, "batch_size": 30, "num_epochs": 82, "optimizer": "SGD"}, "time_since_restore": 9776.463505029678, "iterations_since_restore": 67}
{"train_loss": 0.013306993664009496, "val_loss": 0.012561444053426385, "val_psnr": 19.39538734017998, "val_ssim": 0.5463642356321216, "timestamp": 1727455492, "checkpoint_dir_name": null, "done": false, "training_iteration": 68, "trial_id": "b39b0_00011", "date": "2024-09-27_23-44-52", "time_this_iter_s": 140.47616910934448, "time_total_s": 9916.939674139023, "pid": 4097730, "hostname": "prism-2.apex.cmkl.ac.th", "node_ip": "172.16.101.112", "config": {"architecture": [64, 128, 256], "lr": 0.0007611817967705463, "batch_size": 30, "num_epochs": 82, "optimizer": "SGD"}, "time_since_restore": 9916.939674139023, "iterations_since_restore": 68}
{"train_loss": 0.013327432418009266, "val_loss": 0.012511841156519949, "val_psnr": 19.42699902789971, "val_ssim": 0.5476691722025474, "timestamp": 1727455633, "checkpoint_dir_name": null, "done": false, "training_iteration": 69, "trial_id": "b39b0_00011", "date": "2024-09-27_23-47-13", "time_this_iter_s": 141.24866127967834, "time_total_s": 10058.188335418701, "pid": 4097730, "hostname": "prism-2.apex.cmkl.ac.th", "node_ip": "172.16.101.112", "config": {"architecture": [64, 128, 256], "lr": 0.0007611817967705463, "batch_size": 30, "num_epochs": 82, "optimizer": "SGD"}, "time_since_restore": 10058.188335418701, "iterations_since_restore": 69}
{"train_loss": 0.013383053584257142, "val_loss": 0.0125395815866068, "val_psnr": 19.405952743496663, "val_ssim": 0.5470939022228122, "timestamp": 1727455789, "checkpoint_dir_name": null, "done": false, "training_iteration": 70, "trial_id": "b39b0_00011", "date": "2024-09-27_23-49-49", "time_this_iter_s": 155.7453863620758, "time_total_s": 10213.933721780777, "pid": 4097730, "hostname": "prism-2.apex.cmkl.ac.th", "node_ip": "172.16.101.112", "config": {"architecture": [64, 128, 256], "lr": 0.0007611817967705463, "batch_size": 30, "num_epochs": 82, "optimizer": "SGD"}, "time_since_restore": 10213.933721780777, "iterations_since_restore": 70}
{"train_loss": 0.013284621780039743, "val_loss": 0.01252173081971705, "val_psnr": 19.42357835333688, "val_ssim": 0.5479774197886388, "timestamp": 1727455940, "checkpoint_dir_name": null, "done": false, "training_iteration": 71, "trial_id": "b39b0_00011", "date": "2024-09-27_23-52-20", "time_this_iter_s": 151.53841829299927, "time_total_s": 10365.472140073776, "pid": 4097730, "hostname": "prism-2.apex.cmkl.ac.th", "node_ip": "172.16.101.112", "config": {"architecture": [64, 128, 256], "lr": 0.0007611817967705463, "batch_size": 30, "num_epochs": 82, "optimizer": "SGD"}, "time_since_restore": 10365.472140073776, "iterations_since_restore": 71}
{"train_loss": 0.013279630754841492, "val_loss": 0.012548893834464251, "val_psnr": 19.404739034588463, "val_ssim": 0.5475250941043098, "timestamp": 1727456106, "checkpoint_dir_name": null, "done": false, "training_iteration": 72, "trial_id": "b39b0_00011", "date": "2024-09-27_23-55-06", "time_this_iter_s": 165.72644352912903, "time_total_s": 10531.198583602905, "pid": 4097730, "hostname": "prism-2.apex.cmkl.ac.th", "node_ip": "172.16.101.112", "config": {"architecture": [64, 128, 256], "lr": 0.0007611817967705463, "batch_size": 30, "num_epochs": 82, "optimizer": "SGD"}, "time_since_restore": 10531.198583602905, "iterations_since_restore": 72}
{"train_loss": 0.013338892075698822, "val_loss": 0.012511116052046418, "val_psnr": 19.427056822581076, "val_ssim": 0.5480901781966289, "timestamp": 1727456263, "checkpoint_dir_name": null, "done": false, "training_iteration": 73, "trial_id": "b39b0_00011", "date": "2024-09-27_23-57-43", "time_this_iter_s": 156.73899459838867, "time_total_s": 10687.937578201294, "pid": 4097730, "hostname": "prism-2.apex.cmkl.ac.th", "node_ip": "172.16.101.112", "config": {"architecture": [64, 128, 256], "lr": 0.0007611817967705463, "batch_size": 30, "num_epochs": 82, "optimizer": "SGD"}, "time_since_restore": 10687.937578201294, "iterations_since_restore": 73}
{"train_loss": 0.013264400199986995, "val_loss": 0.012532168505713344, "val_psnr": 19.409378405988928, "val_ssim": 0.5471130301107963, "timestamp": 1727456409, "checkpoint_dir_name": null, "done": false, "training_iteration": 74, "trial_id": "b39b0_00011", "date": "2024-09-28_00-00-09", "time_this_iter_s": 145.73286938667297, "time_total_s": 10833.670447587967, "pid": 4097730, "hostname": "prism-2.apex.cmkl.ac.th", "node_ip": "172.16.101.112", "config": {"architecture": [64, 128, 256], "lr": 0.0007611817967705463, "batch_size": 30, "num_epochs": 82, "optimizer": "SGD"}, "time_since_restore": 10833.670447587967, "iterations_since_restore": 74}
{"train_loss": 0.013259046477032825, "val_loss": 0.012378967753611504, "val_psnr": 19.456873166761408, "val_ssim": 0.5490592264582713, "timestamp": 1727456554, "checkpoint_dir_name": null, "done": false, "training_iteration": 75, "trial_id": "b39b0_00011", "date": "2024-09-28_00-02-34", "time_this_iter_s": 145.77243542671204, "time_total_s": 10979.442883014679, "pid": 4097730, "hostname": "prism-2.apex.cmkl.ac.th", "node_ip": "172.16.101.112", "config": {"architecture": [64, 128, 256], "lr": 0.0007611817967705463, "batch_size": 30, "num_epochs": 82, "optimizer": "SGD"}, "time_since_restore": 10979.442883014679, "iterations_since_restore": 75}
{"train_loss": 0.013220603582449258, "val_loss": 0.012475039437413215, "val_psnr": 19.442066253245326, "val_ssim": 0.5492690975914399, "timestamp": 1727456680, "checkpoint_dir_name": null, "done": false, "training_iteration": 76, "trial_id": "b39b0_00011", "date": "2024-09-28_00-04-40", "time_this_iter_s": 125.94694828987122, "time_total_s": 11105.38983130455, "pid": 4097730, "hostname": "prism-2.apex.cmkl.ac.th", "node_ip": "172.16.101.112", "config": {"architecture": [64, 128, 256], "lr": 0.0007611817967705463, "batch_size": 30, "num_epochs": 82, "optimizer": "SGD"}, "time_since_restore": 11105.38983130455, "iterations_since_restore": 76}
{"train_loss": 0.013151909767184406, "val_loss": 0.012326537710614503, "val_psnr": 19.479991998036173, "val_ssim": 0.54951530593882, "timestamp": 1727456808, "checkpoint_dir_name": null, "done": false, "training_iteration": 77, "trial_id": "b39b0_00011", "date": "2024-09-28_00-06-48", "time_this_iter_s": 128.1120569705963, "time_total_s": 11233.501888275146, "pid": 4097730, "hostname": "prism-2.apex.cmkl.ac.th", "node_ip": "172.16.101.112", "config": {"architecture": [64, 128, 256], "lr": 0.0007611817967705463, "batch_size": 30, "num_epochs": 82, "optimizer": "SGD"}, "time_since_restore": 11233.501888275146, "iterations_since_restore": 77}
{"train_loss": 0.013238024633610622, "val_loss": 0.012360368357039988, "val_psnr": 19.470442255530585, "val_ssim": 0.5500569874718785, "timestamp": 1727456936, "checkpoint_dir_name": null, "done": false, "training_iteration": 78, "trial_id": "b39b0_00011", "date": "2024-09-28_00-08-56", "time_this_iter_s": 127.52551770210266, "time_total_s": 11361.02740597725, "pid": 4097730, "hostname": "prism-2.apex.cmkl.ac.th", "node_ip": "172.16.101.112", "config": {"architecture": [64, 128, 256], "lr": 0.0007611817967705463, "batch_size": 30, "num_epochs": 82, "optimizer": "SGD"}, "time_since_restore": 11361.02740597725, "iterations_since_restore": 78}
{"train_loss": 0.013147079648915679, "val_loss": 0.012409222316928209, "val_psnr": 19.465305185794882, "val_ssim": 0.5510198910509546, "timestamp": 1727457065, "checkpoint_dir_name": null, "done": false, "training_iteration": 79, "trial_id": "b39b0_00011", "date": "2024-09-28_00-11-05", "time_this_iter_s": 129.3314266204834, "time_total_s": 11490.358832597733, "pid": 4097730, "hostname": "prism-2.apex.cmkl.ac.th", "node_ip": "172.16.101.112", "config": {"architecture": [64, 128, 256], "lr": 0.0007611817967705463, "batch_size": 30, "num_epochs": 82, "optimizer": "SGD"}, "time_since_restore": 11490.358832597733, "iterations_since_restore": 79}
{"train_loss": 0.013106445753946901, "val_loss": 0.012400439418852329, "val_psnr": 19.466210839043583, "val_ssim": 0.5501679809466005, "timestamp": 1727457193, "checkpoint_dir_name": null, "done": false, "training_iteration": 80, "trial_id": "b39b0_00011", "date": "2024-09-28_00-13-13", "time_this_iter_s": 127.3329553604126, "time_total_s": 11617.691787958145, "pid": 4097730, "hostname": "prism-2.apex.cmkl.ac.th", "node_ip": "172.16.101.112", "config": {"architecture": [64, 128, 256], "lr": 0.0007611817967705463, "batch_size": 30, "num_epochs": 82, "optimizer": "SGD"}, "time_since_restore": 11617.691787958145, "iterations_since_restore": 80}
{"train_loss": 0.013116770940832793, "val_loss": 0.012364740371704102, "val_psnr": 19.477670286855485, "val_ssim": 0.55103036181132, "timestamp": 1727457319, "checkpoint_dir_name": null, "done": false, "training_iteration": 81, "trial_id": "b39b0_00011", "date": "2024-09-28_00-15-19", "time_this_iter_s": 125.86323833465576, "time_total_s": 11743.5550262928, "pid": 4097730, "hostname": "prism-2.apex.cmkl.ac.th", "node_ip": "172.16.101.112", "config": {"architecture": [64, 128, 256], "lr": 0.0007611817967705463, "batch_size": 30, "num_epochs": 82, "optimizer": "SGD"}, "time_since_restore": 11743.5550262928, "iterations_since_restore": 81}
{"train_loss": 0.013095036855665966, "val_loss": 0.012462217197753488, "val_psnr": 19.444703283348364, "val_ssim": 0.5498136945217847, "timestamp": 1727457447, "checkpoint_dir_name": null, "done": false, "training_iteration": 82, "trial_id": "b39b0_00011", "date": "2024-09-28_00-17-27", "time_this_iter_s": 128.47989964485168, "time_total_s": 11872.034925937653, "pid": 4097730, "hostname": "prism-2.apex.cmkl.ac.th", "node_ip": "172.16.101.112", "config": {"architecture": [64, 128, 256], "lr": 0.0007611817967705463, "batch_size": 30, "num_epochs": 82, "optimizer": "SGD"}, "time_since_restore": 11872.034925937653, "iterations_since_restore": 82}
